thonnycontrib/thonny_etboard_all/__init__.py
thonnycontrib/thonny_etboard_all/__pycache__/__init__.cpython-39.pyc
thonny_etboard_all-1.0.0.dist-info/LICENSE
thonny_etboard_all-1.0.0.dist-info/METADATA
thonny_etboard_all-1.0.0.dist-info/WHEEL
thonny_etboard_all-1.0.0.dist-info/top_level.txt
thonny_etboard_all-1.0.0.dist-info/RECORD
