Metadata-Version: 2.1
Name: thonny-etboard-all
Version: 1.0.0
Summary: ET보드 전체 패키지
Home-page: http://et.ketri.re.kr/
Author: KETRi
Author-email: ketri3000@gmail.com
License: UNKNOWN
Project-URL: Bug Tracker, http://et.ketri.re.kr/
Platform: UNKNOWN
Classifier: Programming Language :: Python :: 3
Classifier: License :: OSI Approved :: MIT License
Classifier: Operating System :: OS Independent
Requires-Python: >=3.6
License-File: LICENSE
Requires-Dist: thonny (>=3.3.11)
Requires-Dist: thonny-etboard-basic-examples
Requires-Dist: thonny-etboard-micropython-firmware
